structlog_pretty/__init__.py
structlog_pretty/processors.py
structlog_pretty/utils.py
structlog_pretty-0.4.3.dist-info/LICENSE
structlog_pretty-0.4.3.dist-info/METADATA
structlog_pretty-0.4.3.dist-info/WHEEL
structlog_pretty-0.4.3.dist-info/top_level.txt
structlog_pretty-0.4.3.dist-info/RECORD
