Metadata-Version: 2.1
Name: structlog-pretty
Version: 0.4.3
Summary: A collection of structlog processors for prettier output
Home-page: https://github.com/underyx/structlog-pretty
Download-URL: https://github.com/underyx/structlog-pretty/releases
Author: Bence Nagy
Author-email: bence@underyx.me
Maintainer: Bence Nagy
Maintainer-email: bence@underyx.me
Classifier: Development Status :: 3 - Alpha
Classifier: License :: OSI Approved :: MIT License
Classifier: Operating System :: OS Independent
Classifier: Programming Language :: Python :: 3 :: Only
License-File: LICENSE
Requires-Dist: pygments ==2.*
Provides-Extra: fast
Requires-Dist: lxml ==5.* ; extra == 'fast'
Requires-Dist: orjson ==3.* ; extra == 'fast'
